{
	"cmake" : 
	{
		"generator" : 
		{
			"multiConfig" : true,
			"name" : "Visual Studio 17 2022",
			"platform" : "win32"
		},
		"paths" : 
		{
			"cmake" : "C:/Program Files (x86)/cmake-3.29.1-windows-x86_64/bin/cmake.exe",
			"cpack" : "C:/Program Files (x86)/cmake-3.29.1-windows-x86_64/bin/cpack.exe",
			"ctest" : "C:/Program Files (x86)/cmake-3.29.1-windows-x86_64/bin/ctest.exe",
			"root" : "C:/Program Files (x86)/cmake-3.29.1-windows-x86_64/share/cmake-3.29"
		},
		"version" : 
		{
			"isDirty" : false,
			"major" : 3,
			"minor" : 29,
			"patch" : 1,
			"string" : "3.29.1",
			"suffix" : ""
		}
	},
	"objects" : 
	[
		{
			"jsonFile" : "codemodel-v2-80173887e56764713143.json",
			"kind" : "codemodel",
			"version" : 
			{
				"major" : 2,
				"minor" : 7
			}
		},
		{
			"jsonFile" : "cache-v2-3f1532492e579ae426d9.json",
			"kind" : "cache",
			"version" : 
			{
				"major" : 2,
				"minor" : 0
			}
		},
		{
			"jsonFile" : "cmakeFiles-v1-b62267353b7e2da2beea.json",
			"kind" : "cmakeFiles",
			"version" : 
			{
				"major" : 1,
				"minor" : 0
			}
		},
		{
			"jsonFile" : "toolchains-v1-db6d36fb1561746e13c2.json",
			"kind" : "toolchains",
			"version" : 
			{
				"major" : 1,
				"minor" : 0
			}
		}
	],
	"reply" : 
	{
		"client-vscode" : 
		{
			"query.json" : 
			{
				"requests" : 
				[
					{
						"kind" : "cache",
						"version" : 2
					},
					{
						"kind" : "codemodel",
						"version" : 2
					},
					{
						"kind" : "toolchains",
						"version" : 1
					},
					{
						"kind" : "cmakeFiles",
						"version" : 1
					}
				],
				"responses" : 
				[
					{
						"jsonFile" : "cache-v2-3f1532492e579ae426d9.json",
						"kind" : "cache",
						"version" : 
						{
							"major" : 2,
							"minor" : 0
						}
					},
					{
						"jsonFile" : "codemodel-v2-80173887e56764713143.json",
						"kind" : "codemodel",
						"version" : 
						{
							"major" : 2,
							"minor" : 7
						}
					},
					{
						"jsonFile" : "toolchains-v1-db6d36fb1561746e13c2.json",
						"kind" : "toolchains",
						"version" : 
						{
							"major" : 1,
							"minor" : 0
						}
					},
					{
						"jsonFile" : "cmakeFiles-v1-b62267353b7e2da2beea.json",
						"kind" : "cmakeFiles",
						"version" : 
						{
							"major" : 1,
							"minor" : 0
						}
					}
				]
			}
		}
	}
}
